<?xml version="1.0" encoding="UTF-8" ?> 
<!-- Tutorial_02_UI_Setup (HTML and CSS) -->
<Module>
	<!-- 
	* STEP 1
	* Let's rename our application and set a default height for the gadget to 250 in ModulePrefs
	-->
	<ModulePrefs title="Tutorial_02_UI_Setup" height="250">
	</ModulePrefs>
	<Content type="html">
		<![CDATA[
			<!-- 
			* STEP 2
			* Add some basic HTML structure to our gadget
			-->
			<div id="app">
				<div id="header"><h2>OpenSocial Tutorial Tool</h2></div>
				<div id="body"></div>
				<div id="footer"></div>
			</div>
			
			<!-- 
			*STEP 3
			* Add CSS styling to set properties for app, header, body and footer elements.
			-->
			<link rel="stylesheet" type="text/css" href="https://www.googledrive.com/host/0B0DPCg3D7fj6dDBLUEdsclhtazg">
		]]>
	</Content>
</Module>